cyberpy/__init__.py
cyberpy/_transaction.py
cyberpy/_typing.py
cyberpy/_wallet.py
cyberpy/typing.py
cyberpy/interfaces/__init__.py
cyberpy/interfaces/any_pb2.py
cyberpy/interfaces/coin_pb2.py
cyberpy/interfaces/gogo_pb2.py
cyberpy/interfaces/msg_link_pb2.py
cyberpy/interfaces/msg_send_pb2.py
cyberpy/interfaces/pubkey_pb2.py
cyberpy/interfaces/signing_pb2.py
cyberpy/interfaces/tx_pb2.py
cyberpy-1.0.6.dist-info/LICENSE
cyberpy-1.0.6.dist-info/METADATA
cyberpy-1.0.6.dist-info/WHEEL
cyberpy-1.0.6.dist-info/top_level.txt
cyberpy-1.0.6.dist-info/RECORD
