Metadata-Version: 2.1
Name: cyberpy
Version: 1.0.6
Summary: Tools for Cyber wallet management, offline transaction signing and broadcasting
Home-page: https://github.com/SaveTheAles/cyberpy
Author: alpuchilo
Author-email: ales.puchilo@gmail.com
License: MIT
Platform: UNKNOWN
Requires-Dist: ecdsa
Requires-Dist: bech32
Requires-Dist: hdwallets
Requires-Dist: mnemonic
Requires-Dist: typing-extensions
Requires-Dist: requests
